selo/__init__.py
selo/browser.py
selo/db.py
selo/driver_config.py
selo/http_request.py
selo/utils.py
selo-1.7.0.dist-info/METADATA
selo-1.7.0.dist-info/WHEEL
selo-1.7.0.dist-info/top_level.txt
selo-1.7.0.dist-info/RECORD
