Metadata-Version: 2.4
Name: selo
Version: 1.7.0
Summary: A simple Selenium wrapper
Author: MaYunFeng
Author-email: you@example.com
License: MIT
Classifier: Programming Language :: Python :: 3
Classifier: License :: OSI Approved :: MIT License
Requires-Python: >=3.13
Requires-Dist: selenium>=4.33.0
Requires-Dist: attrs>=25.3.0
Requires-Dist: blinker>=1.9.0
Requires-Dist: certifi>=2025.4.26
Requires-Dist: cffi>=1.17.1
Requires-Dist: charset-normalizer>=3.4.2
Requires-Dist: click>=8.2.1
Requires-Dist: colorama>=0.4.6
Requires-Dist: h11>=0.16.0
Requires-Dist: idna>=3.10
Requires-Dist: itsdangerous>=2.2.0
Requires-Dist: Jinja2>=3.1.6
Requires-Dist: MarkupSafe>=3.0.2
Requires-Dist: MouseInfo>=0.1.3
Requires-Dist: outcome>=1.3.0.post0
Requires-Dist: PyAutoGUI>=0.9.54
Requires-Dist: pycparser>=2.22
Requires-Dist: PyGetWindow>=0.0.9
Requires-Dist: PyMsgBox>=1.0.9
Requires-Dist: pyperclip>=1.9.0
Requires-Dist: PyRect>=0.2.0
Requires-Dist: PyScreeze>=1.0.1
Requires-Dist: PySocks>=1.7.1
Requires-Dist: pytweening>=1.2.0
Requires-Dist: PyYAML>=6.0.2
Requires-Dist: requests>=2.32.4
Requires-Dist: setuptools>=80.9.0
Requires-Dist: sniffio>=1.3.1
Requires-Dist: sortedcontainers>=2.4.0
Requires-Dist: trio>=0.30.0
Requires-Dist: trio-websocket>=0.12.2
Requires-Dist: typing_extensions>=4.13.2
Requires-Dist: urllib3>=2.4.0
Requires-Dist: websocket-client>=1.8.0
Requires-Dist: Werkzeug>=3.1.3
Requires-Dist: wsproto>=1.2.0
Dynamic: author
Dynamic: author-email
Dynamic: classifier
Dynamic: description
Dynamic: description-content-type
Dynamic: license
Dynamic: requires-dist
Dynamic: requires-python
Dynamic: summary
